bqx/__init__.py
bqx/_func.py
bqx/_func_generator.py
bqx/abstract.py
bqx/func.py
bqx/parts.py
bqx/query.py
bqx-0.4.0.dist-info/DESCRIPTION.rst
bqx-0.4.0.dist-info/METADATA
bqx-0.4.0.dist-info/RECORD
bqx-0.4.0.dist-info/WHEEL
bqx-0.4.0.dist-info/metadata.json
bqx-0.4.0.dist-info/top_level.txt
