Metadata-Version: 2.0
Name: bqx
Version: 0.4.0
Summary: Query generator for Google BigQuery and other SQL environments
Home-page: https://github.com/fuller-inc/bqx
Author: Takumi Sueda
Author-email: takumi.sueda@fuller.co.jp
License: BSD License
Platform: UNKNOWN
Classifier: Development Status :: 4 - Beta
Classifier: Environment :: Console
Classifier: Intended Audience :: Developers
Classifier: Intended Audience :: Science/Research
Classifier: License :: OSI Approved :: BSD License
Classifier: Operating System :: OS Independent
Classifier: Programming Language :: Python
Classifier: Programming Language :: Python :: 3
Classifier: Programming Language :: Python :: 3.5
Classifier: Programming Language :: SQL
Classifier: Topic :: Database
Classifier: Topic :: Software Development :: Code Generators
